{
    "movies" : [
        {
            "id": "rambo",
            "tiitle": "Rambo",
            "year": 1985,
            "score": 8
        },
        {
            "id": "spiderman",
            "tiitle": "Spiderman",
            "year": 2004,
            "score": 9
        },
        {
            "id": "superman",
            "tiitle": "Superman",
            "year": 2000,
            "score": 7
        },
        {
            "id": "batman",
            "tiitle": "Batman",
            "year": 2001,
            "score": 5
        }

    ]
}